{
  "color-basic-100": "#272829",
  "color-basic-200": "#F5F5F5",
  "color-basic-300": "#F5F5F5",
  "color-basic-400": "#D4D4D4",
  "color-basic-500": "#B3B3B3",
  "color-basic-600": "#808080",
  "color-basic-700": "#4A4A4A",
  "color-basic-800": "#F5F5F5",
  "color-basic-900": "#292929",
  "color-basic-1000": "#272829",
  "color-basic-1100": "#272829",
  "color-primary-100": "#F9F9F9",
  "color-primary-200": "#F4F4F4",
  "color-primary-300": "#DEDEDE",
  "color-primary-400": "#BEBEBE",
  "color-primary-500": "#949494",
  "color-primary-600": "#7F6C6D",
  "color-primary-700": "#6A4A50",
  "color-primary-800": "#552F39",
  "color-primary-900": "#471C2B",
  "color-success-100": "#F0FCD8",
  "color-success-200": "#DEFAB1",
  "color-success-300": "#C2F088",
  "color-success-400": "#A4E167",
  "color-success-500": "#7CCE39",
  "color-success-600": "#5FB129",
  "color-success-700": "#45941C",
  "color-success-800": "#2F7712",
  "color-success-900": "#1F620A",
  "color-info-100": "#DAF6FE",
  "color-info-200": "#B6E9FE",
  "color-info-300": "#91D8FE",
  "color-info-400": "#76C7FD",
  "color-info-500": "#49ABFC",
  "color-info-600": "#3585D8",
  "color-info-700": "#2464B5",
  "color-info-800": "#174692",
  "color-info-900": "#0E3178",
  "color-warning-100": "#FEF6CB",
  "color-warning-200": "#FEEA98",
  "color-warning-300": "#FEDB65",
  "color-warning-400": "#FDCC3F",
  "color-warning-500": "#FCB400",
  "color-warning-600": "#D89400",
  "color-warning-700": "#B57600",
  "color-warning-800": "#925B00",
  "color-warning-900": "#784800",
  "color-danger-100": "#FFEAE6",
  "color-danger-200": "#FFD0CD",
  "color-danger-300": "#FFB5B8",
  "color-danger-400": "#FFA2AF",
  "color-danger-500": "#FF84A1",
  "color-danger-600": "#DB6089",
  "color-danger-700": "#B74274",
  "color-danger-800": "#932A61",
  "color-danger-900": "#7A1955"
}